[
  {
    "标题": "赞皇县2026年革命老区转移支付道路修建项目项目(01标段（包）)招标公告",
    "链接": "https://www.ggzy.gov.cn/information/deal/html/a/130000/0101/20260308/00138dccdcaa78294e2bbd7622a3f8491ca5.html",
    "发布日期": "2026-03-08",
    "省份": "河北省",
    "来源平台": "石家庄公共资源交易网",
    "业务类型": "工程建设",
    "信息类型": "招标/资审公告",
    "行业": ""
  },
  {
    "标题": "赞皇县2026年革命老区转移支付道路修建项目监理项目(01标段（包）)招标公告",
    "链接": "https://www.ggzy.gov.cn/information/deal/html/a/130000/0101/20260308/00138b73299939494b99bbe90fe18dd1a744.html",
    "发布日期": "2026-03-08",
    "省份": "河北省",
    "来源平台": "石家庄公共资源交易网",
    "业务类型": "工程建设",
    "信息类型": "招标/资审公告",
    "行业": ""
  },
  {
    "标题": "新余博信工程咨询有限公司关于渝水区妇幼保健院新建项目化学发光仪、胃肠镜工作清洗站等医疗设备采购项目（JXZFCG-BX2025-45）的询价采购公告",
    "链接": "https://www.ggzy.gov.cn/information/deal/html/a/360000/0201/20260308/0036e701e44c8e6544b1b90dba3107ed1500.html",
    "发布日期": "2026-03-08",
    "省份": "江西省",
    "来源平台": "新余市公共资源交易中心",
    "业务类型": "政府采购",
    "信息类型": "采购/资审公告",
    "行业": ""
  },
  {
    "标题": "江西省鼎跃招标咨询有限公司关于江西省中西医结合医院磁共振维保服务项目（采购编号：JXDY2026-FW-C0001）竞争性磋商公告",
    "链接": "https://www.ggzy.gov.cn/information/deal/html/a/360000/0201/20260308/0036d0b9198045b14eeba2152a66f6981ca4.html",
    "发布日期": "2026-03-08",
    "省份": "江西省",
    "来源平台": "南昌市公共资源交易中心",
    "业务类型": "政府采购",
    "信息类型": "采购/资审公告",
    "行业": ""
  },
  {
    "标题": "江西江楚项目管理咨询有限公司关于赣州市第五人民医院药品分包机项目（项目编号：JXJC2025-GZ-G009品目一）的电子化公开招标公告",
    "链接": "https://www.ggzy.gov.cn/information/deal/html/a/360000/0201/20260308/00369d61c63145ae4c18aaef728490731ace.html",
    "发布日期": "2026-03-08",
    "省份": "江西省",
    "来源平台": "赣州市公共资源交易中心",
    "业务类型": "政府采购",
    "信息类型": "采购/资审公告",
    "行业": ""
  },
  {
    "标题": "上饶市君荟招标代理有限公司关于上饶高铁经济试验区灵溪街道办事处灵溪街道2025-2026年度松材线虫病防控（项目编号：JHDLCG-2026-002#-1）公开招标公告",
    "链接": "https://www.ggzy.gov.cn/information/deal/html/a/360000/0201/20260308/00368dddcdabe5bc4bd8bbd61fd1cd4b1abb.html",
    "发布日期": "2026-03-08",
    "省份": "江西省",
    "来源平台": "上饶市公共资源交易中心",
    "业务类型": "政府采购",
    "信息类型": "采购/资审公告",
    "行业": ""
  },
  {
    "标题": "江西新生代工程项目管理有限公司关于安福县数字经济与电商融合创新中心改造升级项目（项目编号：JXXSD【2026】-CG02）竞争性谈判采购公告",
    "链接": "https://www.ggzy.gov.cn/information/deal/html/a/360000/0201/20260308/00366ebca306f6224ab78c6f8d61ce4d0787.html",
    "发布日期": "2026-03-08",
    "省份": "江西省",
    "来源平台": "吉安市公共资源交易中心",
    "业务类型": "政府采购",
    "信息类型": "采购/资审公告",
    "行业": ""
  },
  {
    "标题": "赣州市银欣项目咨询管理有限公司关于江西省龙南市教育体育局采购一批办学设备项目（项目编号：GZYX2026-LN-G005） 不见面电子化公开招标公告",
    "链接": "https://www.ggzy.gov.cn/information/deal/html/a/360000/0201/20260308/003664697804fe204012bbf8ccd926023f37.html",
    "发布日期": "2026-03-08",
    "省份": "江西省",
    "来源平台": "赣州市公共资源交易中心",
    "业务类型": "政府采购",
    "信息类型": "采购/资审公告",
    "行业": ""
  },
  {
    "标题": "江西年华工程咨询有限公司关于九江市应急管理局2025年市本级抗旱装备采购项目（项目编号：JXNH2026J003）竞争性谈判采购公告",
    "链接": "https://www.ggzy.gov.cn/information/deal/html/a/360000/0201/20260308/0036530f4b0407494554bcad8a88e6339552.html",
    "发布日期": "2026-03-08",
    "省份": "江西省",
    "来源平台": "九江市公共资源交易中心",
    "业务类型": "政府采购",
    "信息类型": "采购/资审公告",
    "行业": ""
  },
  {
    "标题": "江西江楚项目管理咨询有限公司关于赣州市第五人民医院药品分包机项目（项目编号：JXJC2025-GZ-G009品目二）的电子化公开招标公告",
    "链接": "https://www.ggzy.gov.cn/information/deal/html/a/360000/0201/20260308/00362295198307ab4fa4a3f2f00659d78857.html",
    "发布日期": "2026-03-08",
    "省份": "江西省",
    "来源平台": "赣州市公共资源交易中心",
    "业务类型": "政府采购",
    "信息类型": "采购/资审公告",
    "行业": ""
  },
  {
    "标题": "上饶市筎意招标代理有限公司关于上饶市广信区人民医院2026年度洗涤服务采购项目（项目编号:RYZFCG-2026-018）竞争性磋商采购公告",
    "链接": "https://www.ggzy.gov.cn/information/deal/html/a/360000/0201/20260308/003619496d66808b4e0cb32be7bbbebb795f.html",
    "发布日期": "2026-03-08",
    "省份": "江西省",
    "来源平台": "上饶市公共资源交易中心",
    "业务类型": "政府采购",
    "信息类型": "采购/资审公告",
    "行业": ""
  },
  {
    "标题": "科尔沁右翼中旗农牧和科技局一批闲置颗粒机、粉碎机等秸秆转化设备打包转让",
    "链接": "https://www.ggzy.gov.cn/information/deal/html/a/150000/0501/20260308/0015c10557a6715f4277b531f36f1a5e1773.html",
    "发布日期": "2026-03-08",
    "省份": "内蒙古自治区",
    "来源平台": "E交易电子平台信息系统",
    "业务类型": "国有产权",
    "信息类型": "挂牌披露",
    "行业": ""
  }
]